{
  "schema_version": 1,
  "id": "market_commercial_streets_2003_building_levels",
  "map_id": "market_commercial_streets_2003",
  "name": "Market / Commercial Streets 2003 Building Levels",
  "world_width_m": 500,
  "world_height_m": 500,
  "pixel_width": 7000,
  "pixel_height": 7000,
  "pixels_per_meter": 14,
  "origin": "top_left",
  "art_style": "approved MOSUL black-and-white contemporary graphite line art; no stick art or schematic placeholder art; no baked static traffic vehicle ink",
  "max_storeys": 4,
  "level_count": 4,
  "feature_count": 25,
  "building_region_count": 8,
  "levels": [
    {
      "id": "level_01_ground",
      "index": 1,
      "elevation_m": 0,
      "png": "assets/mosul/runtime/maps/market_commercial_streets_2003/levels/level_01_ground.png",
      "alpha": "opaque",
      "blocks_los_default": false,
      "blocks_movement_default": false
    },
    {
      "id": "level_02_roofs_and_second_floor",
      "index": 2,
      "elevation_m": 3,
      "png": "assets/mosul/runtime/maps/market_commercial_streets_2003/levels/level_02_roofs_and_second_floor.png",
      "alpha": "overlay",
      "blocks_los_default": false,
      "blocks_movement_default": false
    },
    {
      "id": "level_03_upper_floor",
      "index": 3,
      "elevation_m": 6,
      "png": "assets/mosul/runtime/maps/market_commercial_streets_2003/levels/level_03_upper_floor.png",
      "alpha": "overlay",
      "blocks_los_default": false,
      "blocks_movement_default": false
    },
    {
      "id": "level_04_roof_access",
      "index": 4,
      "elevation_m": 9,
      "png": "assets/mosul/runtime/maps/market_commercial_streets_2003/levels/level_04_roof_access.png",
      "alpha": "overlay",
      "blocks_los_default": false,
      "blocks_movement_default": false
    }
  ],
  "features": [
    {
      "id": "souq_west_outer_wall_ground",
      "level_id": "level_01_ground",
      "kind": "wall",
      "x": 1374,
      "y": 1053,
      "width": 48,
      "height": 978,
      "blocks_los": true,
      "blocks_movement": true,
      "allows_los": false,
      "allows_movement": false
    },
    {
      "id": "souq_north_outer_wall_ground",
      "level_id": "level_01_ground",
      "kind": "wall",
      "x": 1374,
      "y": 1053,
      "width": 956,
      "height": 48,
      "blocks_los": true,
      "blocks_movement": true,
      "allows_los": false,
      "allows_movement": false
    },
    {
      "id": "souq_east_outer_wall_ground",
      "level_id": "level_01_ground",
      "kind": "wall",
      "x": 2282,
      "y": 1053,
      "width": 48,
      "height": 978,
      "blocks_los": true,
      "blocks_movement": true,
      "allows_los": false,
      "allows_movement": false
    },
    {
      "id": "souq_south_outer_wall_ground",
      "level_id": "level_01_ground",
      "kind": "wall",
      "x": 1374,
      "y": 1983,
      "width": 956,
      "height": 48,
      "blocks_los": true,
      "blocks_movement": true,
      "allows_los": false,
      "allows_movement": false
    },
    {
      "id": "souq_west_door_ground",
      "level_id": "level_01_ground",
      "kind": "door",
      "x": 1374,
      "y": 1480,
      "width": 48,
      "height": 168,
      "blocks_los": false,
      "blocks_movement": false,
      "allows_los": true,
      "allows_movement": true
    },
    {
      "id": "souq_east_window_ground",
      "level_id": "level_01_ground",
      "kind": "window",
      "x": 2282,
      "y": 1260,
      "width": 48,
      "height": 132,
      "blocks_los": false,
      "blocks_movement": true,
      "allows_los": true,
      "allows_movement": false
    },
    {
      "id": "souq_south_breach_ground",
      "level_id": "level_01_ground",
      "kind": "breach_hole",
      "x": 1760,
      "y": 1983,
      "width": 220,
      "height": 48,
      "blocks_los": false,
      "blocks_movement": false,
      "allows_los": true,
      "allows_movement": true
    },
    {
      "id": "hotel_block_north_wall_ground",
      "level_id": "level_01_ground",
      "kind": "wall",
      "x": 4917,
      "y": 128,
      "width": 1954,
      "height": 54,
      "blocks_los": true,
      "blocks_movement": true,
      "allows_los": false,
      "allows_movement": false
    },
    {
      "id": "hotel_block_west_wall_ground",
      "level_id": "level_01_ground",
      "kind": "wall",
      "x": 4917,
      "y": 128,
      "width": 54,
      "height": 2031,
      "blocks_los": true,
      "blocks_movement": true,
      "allows_los": false,
      "allows_movement": false
    },
    {
      "id": "hotel_lobby_door_ground",
      "level_id": "level_01_ground",
      "kind": "door",
      "x": 4917,
      "y": 900,
      "width": 54,
      "height": 160,
      "blocks_los": false,
      "blocks_movement": false,
      "allows_los": true,
      "allows_movement": true
    },
    {
      "id": "hotel_stairwell_ground",
      "level_id": "level_01_ground",
      "kind": "stair",
      "x": 6170,
      "y": 420,
      "width": 140,
      "height": 170,
      "blocks_los": false,
      "blocks_movement": false,
      "allows_los": true,
      "allows_movement": true
    },
    {
      "id": "hotel_upper_north_wall_level_2",
      "level_id": "level_02_roofs_and_second_floor",
      "kind": "wall",
      "x": 4970,
      "y": 180,
      "width": 1800,
      "height": 44,
      "blocks_los": true,
      "blocks_movement": true,
      "allows_los": false,
      "allows_movement": false
    },
    {
      "id": "hotel_upper_window_row_level_2",
      "level_id": "level_02_roofs_and_second_floor",
      "kind": "window",
      "x": 5450,
      "y": 180,
      "width": 420,
      "height": 44,
      "blocks_los": false,
      "blocks_movement": true,
      "allows_los": true,
      "allows_movement": false
    },
    {
      "id": "hotel_stairwell_level_2",
      "level_id": "level_02_roofs_and_second_floor",
      "kind": "stair",
      "x": 6170,
      "y": 420,
      "width": 140,
      "height": 170,
      "blocks_los": false,
      "blocks_movement": false,
      "allows_los": true,
      "allows_movement": true
    },
    {
      "id": "hotel_third_floor_parapet_level_3",
      "level_id": "level_03_upper_floor",
      "kind": "roof_edge",
      "x": 5150,
      "y": 250,
      "width": 1200,
      "height": 42,
      "blocks_los": false,
      "blocks_movement": true,
      "allows_los": true,
      "allows_movement": false
    },
    {
      "id": "hotel_third_floor_stair_level_3",
      "level_id": "level_03_upper_floor",
      "kind": "stair",
      "x": 6170,
      "y": 420,
      "width": 140,
      "height": 170,
      "blocks_los": false,
      "blocks_movement": false,
      "allows_los": true,
      "allows_movement": true
    },
    {
      "id": "mosque_courtyard_wall_ground",
      "level_id": "level_01_ground",
      "kind": "wall",
      "x": 2438,
      "y": 4018,
      "width": 764,
      "height": 50,
      "blocks_los": true,
      "blocks_movement": true,
      "allows_los": false,
      "allows_movement": false
    },
    {
      "id": "mosque_gate_ground",
      "level_id": "level_01_ground",
      "kind": "door",
      "x": 2750,
      "y": 4018,
      "width": 160,
      "height": 50,
      "blocks_los": false,
      "blocks_movement": false,
      "allows_los": true,
      "allows_movement": true
    },
    {
      "id": "apartment_row_west_wall_ground",
      "level_id": "level_01_ground",
      "kind": "wall",
      "x": 211,
      "y": 4056,
      "width": 54,
      "height": 2655,
      "blocks_los": true,
      "blocks_movement": true,
      "allows_los": false,
      "allows_movement": false
    },
    {
      "id": "apartment_roof_edge_level_2",
      "level_id": "level_02_roofs_and_second_floor",
      "kind": "roof_edge",
      "x": 265,
      "y": 4100,
      "width": 900,
      "height": 42,
      "blocks_los": false,
      "blocks_movement": true,
      "allows_los": true,
      "allows_movement": false
    },
    {
      "id": "market_stall_line_ground",
      "level_id": "level_01_ground",
      "kind": "wall",
      "x": 2460,
      "y": 3770,
      "width": 800,
      "height": 32,
      "blocks_los": false,
      "blocks_movement": true,
      "allows_los": true,
      "allows_movement": false
    },
    {
      "id": "shopfront_window_ground",
      "level_id": "level_01_ground",
      "kind": "window",
      "x": 2960,
      "y": 1050,
      "width": 240,
      "height": 40,
      "blocks_los": false,
      "blocks_movement": true,
      "allows_los": true,
      "allows_movement": false
    },
    {
      "id": "alley_rubble_breach_ground",
      "level_id": "level_01_ground",
      "kind": "breach_hole",
      "x": 3600,
      "y": 3400,
      "width": 250,
      "height": 150,
      "blocks_los": false,
      "blocks_movement": false,
      "allows_los": true,
      "allows_movement": true
    },
    {
      "id": "workshop_shutter_door_ground",
      "level_id": "level_01_ground",
      "kind": "door",
      "x": 3782,
      "y": 3904,
      "width": 250,
      "height": 46,
      "blocks_los": false,
      "blocks_movement": false,
      "allows_los": true,
      "allows_movement": true
    },
    {
      "id": "ladder_roof_access_level_4",
      "level_id": "level_04_roof_access",
      "kind": "stair",
      "x": 3000,
      "y": 1160,
      "width": 80,
      "height": 90,
      "blocks_los": false,
      "blocks_movement": false,
      "allows_los": true,
      "allows_movement": true
    }
  ],
  "building_regions": [
    {
      "id": "single_storey_shop_row_north",
      "storeys": 1,
      "x": 1374,
      "y": 1053,
      "width": 956,
      "height": 978,
      "roof_level_id": "level_02_roofs_and_second_floor"
    },
    {
      "id": "single_storey_market_stalls",
      "storeys": 1,
      "x": 2500,
      "y": 3550,
      "width": 1100,
      "height": 700,
      "roof_level_id": "level_02_roofs_and_second_floor"
    },
    {
      "id": "two_storey_apartment_row_west",
      "storeys": 2,
      "x": 211,
      "y": 4056,
      "width": 1061,
      "height": 2655,
      "roof_level_id": "level_02_roofs_and_second_floor"
    },
    {
      "id": "three_storey_hotel_east",
      "storeys": 3,
      "x": 4917,
      "y": 128,
      "width": 1954,
      "height": 2031,
      "roof_level_id": "level_04_roof_access"
    },
    {
      "id": "two_storey_workshops_south",
      "storeys": 2,
      "x": 3782,
      "y": 3904,
      "width": 1058,
      "height": 1268,
      "roof_level_id": "level_02_roofs_and_second_floor"
    },
    {
      "id": "single_storey_garage_court",
      "storeys": 1,
      "x": 5031,
      "y": 3911,
      "width": 927,
      "height": 1252,
      "roof_level_id": "level_02_roofs_and_second_floor"
    },
    {
      "id": "three_storey_office_block",
      "storeys": 3,
      "x": 2328,
      "y": 992,
      "width": 898,
      "height": 1205,
      "roof_level_id": "level_04_roof_access"
    },
    {
      "id": "two_storey_mosque_edge",
      "storeys": 2,
      "x": 2438,
      "y": 4018,
      "width": 764,
      "height": 1330,
      "roof_level_id": "level_02_roofs_and_second_floor"
    }
  ]
}
